{
  "protocolSection": {
    "identificationModule": {
      "nctId": "NCT01157481",
      "orgStudyIdInfo": {
        "id": "DEMAND-01"
      },
      "secondaryIdInfos": [
        {
          "id": "UMIN000003856",
          "type": "OTHER",
          "domain": "University hospital Medical Information Network"
        }
      ],
      "organization": {
        "fullName": "Demand Investigators",
        "class": "OTHER"
      },
      "briefTitle": "Diastolic Heart Failure Management by Nifedipine",
      "officialTitle": "Diastolic Heart Failure Management by Nifedipine",
      "acronym": "DEMAND"
    },
    "statusModule": {
      "statusVerifiedDate": "2016-01",
      "overallStatus": "UNKNOWN",
      "lastKnownStatus": "ACTIVE_NOT_RECRUITING",
      "expandedAccessInfo": {
        "hasExpandedAccess": false
      },
      "startDateStruct": {
        "date": "2010-07"
      },
      "primaryCompletionDateStruct": {
        "date": "2016-12",
        "type": "ESTIMATED"
      },
      "completionDateStruct": {
        "date": "2016-12",
        "type": "ESTIMATED"
      },
      "studyFirstSubmitDate": "2010-07-01",
      "studyFirstSubmitQcDate": "2010-07-06",
      "studyFirstPostDateStruct": {
        "date": "2010-07-07",
        "type": "ESTIMATED"
      },
      "lastUpdateSubmitDate": "2016-01-21",
      "lastUpdatePostDateStruct": {
        "date": "2016-01-25",
        "type": "ESTIMATED"
      }
    },
    "sponsorCollaboratorsModule": {
      "responsibleParty": {
        "type": "SPONSOR"
      },
      "leadSponsor": {
        "name": "Demand Investigators",
        "class": "OTHER"
      }
    },
    "oversightModule": {
      "oversightHasDmc": true
    },
    "descriptionModule": {
      "briefSummary": "Patients with heart failure with preserved ejection fraction have a equally high risk for mortality and re-hospitalization as those with reduced ejection fraction. Effective management strategies are critically needed to be established for this type of heart failure. These patients have more hypertensive and ischemic etiology than those with reduced ejection fraction. The investigators hypothesis is that Ca channel blocker nifedipine can improve the heart failure clinical composite response endpoint compared with the conventional treatment in patients with heart failure with hypertension and/or coronary artery disease and preserved ejection fraction (\\>=50%) by echocardiography. This study is multi-center, prospective, randomized, open-label, and blinded-endpoint design."
    },
    "conditionsModule": {
      "conditions": [
        "Diastolic Heart Failure"
      ],
      "keywords": [
        "Diastolic Heart Failure",
        "Heart failure with preserved ejection fraction",
        "nifedipine"
      ]
    },
    "designModule": {
      "studyType": "INTERVENTIONAL",
      "phases": [
        "NA"
      ],
      "designInfo": {
        "allocation": "RANDOMIZED",
        "interventionModel": "PARALLEL",
        "primaryPurpose": "TREATMENT",
        "maskingInfo": {
          "masking": "NONE"
        }
      },
      "enrollmentInfo": {
        "count": 226,
        "type": "ACTUAL"
      }
    },
    "armsInterventionsModule": {
      "armGroups": [
        {
          "label": "Conventional therapy plus nifedipine",
          "type": "EXPERIMENTAL",
          "interventionNames": [
            "Drug: Conventional therapy plus nifedipine"
          ]
        },
        {
          "label": "Conventional therapy",
          "type": "ACTIVE_COMPARATOR",
          "interventionNames": [
            "Drug: Conventional therapy"
          ]
        }
      ],
      "interventions": [
        {
          "type": "DRUG",
          "name": "Conventional therapy plus nifedipine",
          "description": "Participants will receive 10 to 60 mg of sustained-release nifedipine once a day until December 2014",
          "armGroupLabels": [
            "Conventional therapy plus nifedipine"
          ]
        },
        {
          "type": "DRUG",
          "name": "Conventional therapy",
          "description": "Conventional therapy",
          "armGroupLabels": [
            "Conventional therapy"
          ]
        }
      ]
    },
    "outcomesModule": {
      "primaryOutcomes": [
        {
          "measure": "Heart failure clinical composite response endpoint",
          "timeFrame": "up to 53 months"
        }
      ],
      "secondaryOutcomes": [
        {
          "measure": "Death",
          "timeFrame": "up to 53 months"
        },
        {
          "measure": "Cardiovascular death",
          "timeFrame": "up to 53 months"
        },
        {
          "measure": "Hospital admission",
          "timeFrame": "up to 53 months"
        },
        {
          "measure": "Hospital admission for cardiovascular disease",
          "timeFrame": "up to 53 months"
        },
        {
          "measure": "Hospital admission for worsening heart failure",
          "timeFrame": "up to 53 months"
        },
        {
          "measure": "Hospital admission for acute myocardial infarction, angina, coronary artery bypass grafting and percutaneous coronary intervention",
          "timeFrame": "up to 53 months"
        },
        {
          "measure": "Stroke",
          "timeFrame": "up to 53 months"
        }
      ]
    },
    "eligibilityModule": {
      "eligibilityCriteria": "Inclusion Criteria:\n\n1. 20 years and older\n2. Heart failure with history of hypertension and/or coronary artery disease\n3. LVEF \\> or = 50% on echocardiography\n\nExclusion Criteria:\n\n1. Valvular heart diseases with significant regurgitation and/or stenosis\n2. Hypertrophic cardiomyopathy, restrictive cardiomyopathy, arrhythmogenic right ventricular cardiomyopathy, and active myocarditis\n3. Constrictive pericarditis\n4. Cardiogenic shock\n5. Planned coronary artery bypass grafting or percutaneous coronary intervention within 3 months\n6. History of acute coronary syndrome or stroke within 3 months\n7. Pregnancy or breastfeeding\n8. Hypersensitivity or contraindication to nifedipine\n9. Inability to obtain informed consent\n10. Any conditions not suitable for the participation in this trial judged by the investigator",
      "healthyVolunteers": false,
      "sex": "ALL",
      "minimumAge": "20 Years",
      "stdAges": [
        "ADULT",
        "OLDER_ADULT"
      ]
    },
    "contactsLocationsModule": {
      "locations": [
        {
          "facility": "Hokkaido Univestity Hospital",
          "city": "Sapporo",
          "zip": "060-8638",
          "country": "Japan",
          "geoPoint": {
            "lat": 43.06667,
            "lon": 141.35
          }
        }
      ]
    }
  },
  "derivedSection": {
    "miscInfoModule": {
      "versionHolder": "2026-02-18"
    },
    "conditionBrowseModule": {
      "meshes": [
        {
          "id": "D054144",
          "term": "Heart Failure, Diastolic"
        }
      ],
      "ancestors": [
        {
          "id": "D006333",
          "term": "Heart Failure"
        },
        {
          "id": "D006331",
          "term": "Heart Diseases"
        },
        {
          "id": "D002318",
          "term": "Cardiovascular Diseases"
        }
      ]
    },
    "interventionBrowseModule": {
      "meshes": [
        {
          "id": "D009543",
          "term": "Nifedipine"
        }
      ],
      "ancestors": [
        {
          "id": "D004095",
          "term": "Dihydropyridines"
        },
        {
          "id": "D011725",
          "term": "Pyridines"
        },
        {
          "id": "D006573",
          "term": "Heterocyclic Compounds, 1-Ring"
        },
        {
          "id": "D006571",
          "term": "Heterocyclic Compounds"
        }
      ]
    }
  },
  "hasResults": false
}