{
  "protocolSection": {
    "identificationModule": {
      "nctId": "NCT05295303",
      "orgStudyIdInfo": {
        "id": "QIBO_1"
      },
      "organization": {
        "fullName": "The University of Hong Kong",
        "class": "OTHER"
      },
      "briefTitle": "Home-based Remote Monitoring",
      "officialTitle": "Quality Improvements in Post-Myocardial Infarction Management Using Home-Based RemOte Monitoring System (QIBO)",
      "acronym": "QIBO"
    },
    "statusModule": {
      "statusVerifiedDate": "2022-03",
      "overallStatus": "NOT_YET_RECRUITING",
      "expandedAccessInfo": {
        "hasExpandedAccess": false
      },
      "startDateStruct": {
        "date": "2022-07-01",
        "type": "ESTIMATED"
      },
      "primaryCompletionDateStruct": {
        "date": "2025-06-30",
        "type": "ESTIMATED"
      },
      "completionDateStruct": {
        "date": "2026-06-30",
        "type": "ESTIMATED"
      },
      "studyFirstSubmitDate": "2022-03-15",
      "studyFirstSubmitQcDate": "2022-03-15",
      "studyFirstPostDateStruct": {
        "date": "2022-03-25",
        "type": "ACTUAL"
      },
      "lastUpdateSubmitDate": "2022-03-15",
      "lastUpdatePostDateStruct": {
        "date": "2022-03-25",
        "type": "ACTUAL"
      }
    },
    "sponsorCollaboratorsModule": {
      "responsibleParty": {
        "type": "PRINCIPAL_INVESTIGATOR",
        "investigatorFullName": "Dr. Chung-Wah David SIU",
        "investigatorTitle": "Clinical Professor",
        "investigatorAffiliation": "The University of Hong Kong"
      },
      "leadSponsor": {
        "name": "The University of Hong Kong",
        "class": "OTHER"
      }
    },
    "oversightModule": {
      "oversightHasDmc": true,
      "isFdaRegulatedDrug": false,
      "isFdaRegulatedDevice": false
    },
    "descriptionModule": {
      "briefSummary": "Acute myocardial infarction (MI) is a disease of high morbidity and mortality. It is usually caused by atherothrombosis of major epicardial coronary arteries which result in myocardial necrosis. Due to improvement in care systems, availability of revascularizations and better medical treatment, the mortality of MI has generally declined in the past 20 years. Nevertheless, patients survived MI are still at heightened risk of further cardiovascular events and death. Therefore, guideline directed secondary preventive measures are of paramount importance to improve long term outcome. These include adherence to medications and dose titration, risk factor modification, detection of arrhythmia and use of implantable cardio-defibrillator (ICD) as appropriate. In reality, guideline adherence is unsatisfactory and may lead to worse clinical outcomes. The underlying reasons are multi-factorial, including lack of patient education, recognition, motivation or physician inertia. Therefore, newer initiatives are required to reinforce secondary preventive measures.\n\nIn current era of health information technology, remote monitoring and telecommunication emerge to be practice-changing in various aspects of healthcare provision. Particularly for post MI survivors, the early post discharge period is vulnerable and a significant number of patients are readmitted 30 days after leaving hospital. This is not surprising as patients are still in recovering phase on medications titration and many of them may not fully accept they are suffering from a life-threatening condition. Besides, malignant arrhythmia may develop without the protection of ICD which is usually implanted after 40 days post MI as per clinical guidelines. As such, home-based remote monitoring with handheld single-lead electrocardiogram and patch-based continuous holter monitor can potentially detect arrhythmia which prompt early clinical attention. Furthermore, daily blood pressure measurement using dedicated smartphone applications enables physicians and patients to up-titrate medications to desired doses more quickly. This can hopefully strengthen compliance to better achieve guideline recommended treatment targets.\n\nIn the Quality Improvements in Post-Myocardial Infarction Management using Home-Based RemOte Monitoring System trial (QIBO; \"岐伯\" in Chinese), we investigate the feasibility and efficacy of utilizing a home-based remote monitoring system in post MI survivors. We hypothesize that this approach is effective to improve guideline directed treatment utility, cardiovascular risk factors target achievement and clinical outcome.",
      "detailedDescription": "This is a prospective, multi-center, open-labelled, randomized controlled trial. Patients with acute myocardial infarction with primary or early percutaneous coronary intervention (PCI) will be recruited upon hospital discharge. Patients with ST-segment elevation myocardial infarction (STEMI) and non-STEMI will be randomized in a 1:1 ratio to home-based remote management care (Intervention group) or conventional care (Control group) for 17 weeks.\n\nUpon hospital discharge, all patients will be provided with a home-based remote integrated post-MI management system and will be instructed to perform daily routine measurements. Patients randomized to the Intervention group will be given patch-based Holter ECG monitoring till post-MI day 40.\n\nThe home-based remote integrated post-MI management system comprises (1) a patch-based long-term Holter monitoring system, (2) a handheld single-lead electrocardiogram (ECG) recorder, (3) a blood pressure monitor, (4) a patient-facing smartphone application specially designed for the study, and (5) a web-based clinical management system for clinicians.\n\nAll remotely obtained Holter data will be transferred daily via the study smartphone application to detect (1) ventricular arrhythmia, (2) ST-segment change, and (3) atrial fibrillation. Thereafter patients in the Interventional group will be instructed to record a 30-second single-lead ECG using the handheld ECG device every morning or when symptomatic. Patients in both the Intervention group and Control group will be instructed to measure their blood pressure in the morning and evening and input the data through the study smartphone application. All remotely obtained physiological data will be automatically transmitted in real-time to a secured cloud hosting and displayed on a web-based dashboard at the clinicians' offices. Physiological parameters of patients in the Interventional group will be reviewed daily by site investigators with preset algorithms to titrate or modify guideline directed medical therapy through instant communication (electronic communication and/or phone), whereas for the Control group, patient data will be reviewed only at the clinic visits. All patients will be followed up for 17 weeks.\n\nThere will have instruction session for study participants, a study research nurse will educate them on individual cardiovascular risk factors, life-style modification, and the treatment targets. In addition, the risk of recurrent cardiovascular event will be estimated using the Thrombolysis In Myocardial Infarction (TIMI) Risk Score for Secondary Prevention (TRS 2°P) score. The TRS 2°P incorporates 9 readily available clinical characteristics: congestive heart failure, hypertension, diabetes mellitus, age ≥75 years, prior stroke, prior coronary artery bypass graft, peripheral artery disease, estimated glomerular filtration rate \\<60, and smoking to predict recurrent cardiovascular events."
    },
    "conditionsModule": {
      "conditions": [
        "Myocardial Infarction"
      ]
    },
    "designModule": {
      "studyType": "INTERVENTIONAL",
      "phases": [
        "NA"
      ],
      "designInfo": {
        "allocation": "RANDOMIZED",
        "interventionModel": "PARALLEL",
        "interventionModelDescription": "To assess efficacy of home-based remote monitoring in post-myocardial infarction patient for improving guideline directed treatment utility, compared between subjects with home-based remote monitoring and management care (Interventional group) and conventional care (Control group).",
        "primaryPurpose": "TREATMENT",
        "maskingInfo": {
          "masking": "NONE"
        }
      },
      "enrollmentInfo": {
        "count": 344,
        "type": "ESTIMATED"
      }
    },
    "armsInterventionsModule": {
      "armGroups": [
        {
          "label": "Interventional group",
          "type": "EXPERIMENTAL",
          "description": "Subjects will be provided with a home-based remote integrated post-MI management system and will be instructed to perform daily routine measurements. Site investigators will review the physiological parameters of patients randomized to the Intervention group daily and treatment can be initiated or modified accordingly through instant communication (electronic communication and/or phone).",
          "interventionNames": [
            "Device: Remote integrated post-MI management system"
          ]
        },
        {
          "label": "Control group",
          "type": "PLACEBO_COMPARATOR",
          "description": "Subjects will be provided with a home-based remote integrated post-MI management system and will be instructed to perform daily routine measurements. Site investigators will review individual patient physiological parameters and risk factors only during the clinic visits",
          "interventionNames": [
            "Device: Remote integrated post-MI management system"
          ]
        }
      ],
      "interventions": [
        {
          "type": "DEVICE",
          "name": "Remote integrated post-MI management system",
          "description": "The home-based remote integrated post-MI management system comprises (1) a patch-based long-term Holter monitoring system HC3A250 (BISA Technologies (Hong Kong) Limited, Hong Kong SAR, China), (2) a handheld single-lead electrocardiogram (ECG) recorder (Comfit Healthcare Devices Limited, Hong Kong SAR, China), (3) a blood pressure monitor, (4) a patient-facing smartphone application specially designed for the study, and (5) a web-based clinical management system for clinicians",
          "armGroupLabels": [
            "Control group",
            "Interventional group"
          ],
          "otherNames": [
            "Holter monitoring system HC3A250 (BISA Technologies (Hong Kong) Limited, Hong Kong SAR, China)",
            "Single-lead electrocardiogram (ECG) recorder (Comfit Healthcare Devices Limited, Hong Kong SAR, China)"
          ]
        }
      ]
    },
    "outcomesModule": {
      "primaryOutcomes": [
        {
          "measure": "Renin-angiotensin-aldosterone system blockers",
          "description": "Percentage of patients with ≥50% maximal targeted dose (MTD) of renin-angiotensin-aldosterone system blockers",
          "timeFrame": "17 weeks"
        }
      ],
      "secondaryOutcomes": [
        {
          "measure": "Beta-adrenergic blockers",
          "description": "Percentage of patients with ≥50% maximal targeted dose (MTD) of beta-adrenergic blocker2",
          "timeFrame": "17 weeks"
        },
        {
          "measure": "Ivabradine",
          "description": "Percentage of patients with ≥50% maximal targeted dose (MTD) of ivabradine",
          "timeFrame": "17 weeks"
        },
        {
          "measure": "Statin",
          "description": "Percentage of patients with ≥50% maximal targeted dose (MTD) of statin",
          "timeFrame": "17 weeks"
        },
        {
          "measure": "Renin-angiotensin-aldosterone system blockers",
          "description": "Dosage in terms of percentage maximal targeted dose (MTD) of renin-angiotensin-aldosterone system blockers",
          "timeFrame": "17 weeks"
        },
        {
          "measure": "Beta-adrenergic blockers",
          "description": "Dosage in terms of percentage maximal targeted dose (MTD) of beta-adrenergic blockers",
          "timeFrame": "17 weeks"
        },
        {
          "measure": "Ivabradine",
          "description": "Dosage in terms of percentage maximal targeted dose (MTD) of ivabradine",
          "timeFrame": "17 weeks"
        },
        {
          "measure": "Statin",
          "description": "Dosage in terms of percentage maximal targeted dose (MTD) of statin",
          "timeFrame": "17 weeks"
        },
        {
          "measure": "Low density lipoprotein",
          "description": "Occurrence of achieving cardiovascular risk factors target of low density lipoprotein (\\< 1.4 mmol/L or \\>50% reduction)",
          "timeFrame": "17 weeks"
        },
        {
          "measure": "High density lipoprotein",
          "description": "Occurrence of achieving cardiovascular risk factors target of high density lipoprotein (\\> 1.0 mmol/L)",
          "timeFrame": "17 weeks"
        },
        {
          "measure": "Triglyceride",
          "description": "Occurrence of achieving cardiovascular risk factors target of triglyceride (\\< 1.7 mmol/L)",
          "timeFrame": "17 weeks"
        },
        {
          "measure": "Body mass index",
          "description": "Occurrence of achieving cardiovascular risk factors target of body mass index (\\< 25 kg/m2)",
          "timeFrame": "17 weeks"
        },
        {
          "measure": "Resting blood pressure",
          "description": "Occurrence of achieving cardiovascular risk factors target of resting blood pressure (systolic blood pressure within 100 - 120 mmHg and diastolic blood pressure within 60 - 90 mmHg)",
          "timeFrame": "17 weeks"
        },
        {
          "measure": "Resting heart rate",
          "description": "Occurrence of achieving cardiovascular risk factors target of resting heart rate (sinus rhythm 50 - 70 bpm and atrial fibrillation 50 - 110 bpm)",
          "timeFrame": "17 weeks"
        },
        {
          "measure": "Hemoglobin A1C",
          "description": "Occurrence of achieving cardiovascular risk factors target of hemoglobin A1c (\\< 7%)",
          "timeFrame": "17 weeks"
        },
        {
          "measure": "Smoking cessation",
          "description": "Occurrence of achieving cardiovascular risk factors target of smoking cessation",
          "timeFrame": "17 weeks"
        },
        {
          "measure": "Moderate intensity aerobic exercise",
          "description": "Occurrence of achieving cardiovascular risk factors target of moderate intensity aerobic exercise (\\> equivalent of 30 minutes for 5 times per week)",
          "timeFrame": "17 weeks"
        },
        {
          "measure": "Major adverse cardiovascular events",
          "description": "Occurrence of cardiovascular events of composite major adverse cardiovascular events including cardiovascular death from any causes, non-fatal myocardial infarction, unplanned coronary revascularization, and non-fatal stroke",
          "timeFrame": "17 weeks"
        },
        {
          "measure": "Heart failure hospitalization",
          "description": "Occurrence of cardiovascular events of heart failure hospitalization",
          "timeFrame": "17 weeks"
        },
        {
          "measure": "New-onset atrial fibrillation",
          "description": "Occurrence of cardiovascular events of new-onset atrial fibrillation",
          "timeFrame": "17 weeks"
        },
        {
          "measure": "Sudden cardiac arrest",
          "description": "Occurrence of cardiovascular events of sudden cardiac arrest",
          "timeFrame": "17 weeks"
        },
        {
          "measure": "Implantation of automatic implantable cardioverter-defibrillator",
          "description": "Occurrence of cardiovascular events of implantation of automatic implantable cardioverter-defibrillator",
          "timeFrame": "17 weeks"
        },
        {
          "measure": "All cause mortality",
          "description": "Occurrence of cardiovascular events of all cause mortality",
          "timeFrame": "17 weeks"
        }
      ]
    },
    "eligibilityModule": {
      "eligibilityCriteria": "Inclusion Criteria:\n\n* Age ≥ 18 years\n* Hospitalized with acute myocardial infarction as defined as a detection of a rise and/or fall of troponin with at least 1 value above the 99th percentile upper reference limit together with either (1) symptoms of myocardial ischemia, or (2) ECG changes compatible with myocardial ischemia\n* Treated with PCI for culprit lesson\n* Voluntarily agrees to participate by providing written informed consent\n\nExclusion Criteria:\n\n* Complex congenital heart disease\n* Significant valvular stenosis\n* Left ventricular assist device\n* Listed for heart transplant\n* Renal impairment with serum creatinine ≥ 190 μmol/L or on renal replacement therapy\n* Inability or refusal to provide inform consent\n* Short life expectance (\\< 1 year) due to concomitant medical condition(s)\n* Lack of skills in operating simple electronic devices\n* Unavailability of a mobile network service in the place of residence",
      "healthyVolunteers": false,
      "sex": "ALL",
      "minimumAge": "18 Years",
      "stdAges": [
        "ADULT",
        "OLDER_ADULT"
      ]
    },
    "contactsLocationsModule": {
      "centralContacts": [
        {
          "name": "Chun-Ka Wong, Resident",
          "role": "CONTACT",
          "phone": "+852-22553597",
          "email": "emmanuelckwong@gmail.com"
        }
      ],
      "overallOfficials": [
        {
          "name": "Chung-Wah David Siu, Prof",
          "affiliation": "The University of Hong Kong",
          "role": "PRINCIPAL_INVESTIGATOR"
        }
      ],
      "locations": [
        {
          "facility": "The University of Hong Kong, Queen Mary Hospital",
          "city": "Hong Kong",
          "country": "Hong Kong",
          "contacts": [
            {
              "name": "Chung-Wah David Siu, Professor",
              "role": "CONTACT",
              "phone": "22553597",
              "email": "cwdsiu@hku.hk"
            }
          ],
          "geoPoint": {
            "lat": 22.27832,
            "lon": 114.17469
          }
        }
      ]
    },
    "ipdSharingStatementModule": {
      "ipdSharing": "UNDECIDED"
    }
  },
  "derivedSection": {
    "miscInfoModule": {
      "versionHolder": "2026-02-18"
    },
    "conditionBrowseModule": {
      "meshes": [
        {
          "id": "D009203",
          "term": "Myocardial Infarction"
        }
      ],
      "ancestors": [
        {
          "id": "D017202",
          "term": "Myocardial Ischemia"
        },
        {
          "id": "D006331",
          "term": "Heart Diseases"
        },
        {
          "id": "D002318",
          "term": "Cardiovascular Diseases"
        },
        {
          "id": "D014652",
          "term": "Vascular Diseases"
        },
        {
          "id": "D007238",
          "term": "Infarction"
        },
        {
          "id": "D007511",
          "term": "Ischemia"
        },
        {
          "id": "D010335",
          "term": "Pathologic Processes"
        },
        {
          "id": "D013568",
          "term": "Pathological Conditions, Signs and Symptoms"
        },
        {
          "id": "D009336",
          "term": "Necrosis"
        }
      ]
    },
    "interventionBrowseModule": {
      "meshes": [
        {
          "id": "D004562",
          "term": "Electrocardiography"
        }
      ],
      "ancestors": [
        {
          "id": "D006334",
          "term": "Heart Function Tests"
        },
        {
          "id": "D003935",
          "term": "Diagnostic Techniques, Cardiovascular"
        },
        {
          "id": "D019937",
          "term": "Diagnostic Techniques and Procedures"
        },
        {
          "id": "D003933",
          "term": "Diagnosis"
        },
        {
          "id": "D004568",
          "term": "Electrodiagnosis"
        }
      ]
    }
  },
  "hasResults": false
}