{
  "protocolSection": {
    "identificationModule": {
      "nctId": "NCT01308047",
      "orgStudyIdInfo": {
        "id": "CRIST016"
      },
      "organization": {
        "fullName": "Cristália Produtos Químicos Farmacêuticos Ltda.",
        "class": "INDUSTRY"
      },
      "briefTitle": "Comparing Heavy Levobupivacaine With Enantiomeric Excess of 50% and Heavy Racemic Bupivacaine.",
      "officialTitle": "Comparative Study of Non-inferiority Between Heavy Levobupivacaine With Enantiomeric Excess of 50% (Bupivacaine S75: R25) and Heavy Racemic Bupivacaine (Bupivacaine S50: R50) in Spinal Anesthesia for Orthopedic Procedures in the Lower Limbs."
    },
    "statusModule": {
      "statusVerifiedDate": "2014-03",
      "overallStatus": "WITHDRAWN",
      "whyStopped": "The Sponsor has no interest in continuing the study.",
      "expandedAccessInfo": {
        "hasExpandedAccess": false
      },
      "studyFirstSubmitDate": "2011-02-23",
      "studyFirstSubmitQcDate": "2011-03-02",
      "studyFirstPostDateStruct": {
        "date": "2011-03-03",
        "type": "ESTIMATED"
      },
      "lastUpdateSubmitDate": "2014-03-25",
      "lastUpdatePostDateStruct": {
        "date": "2014-03-26",
        "type": "ESTIMATED"
      }
    },
    "sponsorCollaboratorsModule": {
      "responsibleParty": {
        "type": "SPONSOR"
      },
      "leadSponsor": {
        "name": "Cristália Produtos Químicos Farmacêuticos Ltda.",
        "class": "INDUSTRY"
      },
      "collaborators": [
        {
          "name": "Irmandade da Santa Casa de Misericordia de Sao Paulo",
          "class": "OTHER"
        },
        {
          "name": "Serviço Social da Indústria do Papel, Papelão e Cortiça do Estado de São Paulo",
          "class": "UNKNOWN"
        }
      ]
    },
    "oversightModule": {
      "oversightHasDmc": false
    },
    "descriptionModule": {
      "briefSummary": "The purpose of this study is to compare the non-inferiority between Heavy Levobupivacaine with Enantiomeric Excess of 50% and Heavy Racemic Bupivacaine During Spinal Anesthesia for Orthopedic Procedures in the Lower Limbs.",
      "detailedDescription": "The Heavy Levobupivacaine with Enantiomeric Excess of 50% was developed to be a safe local anesthetic replacing the Heavy Racemic Bupivacaine.\n\nThis study will evaluate the non-inferiority regarding efficacy and safety of spinal anesthesia in orthopedic procedures."
    },
    "conditionsModule": {
      "conditions": [
        "Fracture of Lower Limb"
      ]
    },
    "designModule": {
      "studyType": "INTERVENTIONAL",
      "phases": [
        "PHASE3"
      ],
      "designInfo": {
        "allocation": "RANDOMIZED",
        "interventionModel": "PARALLEL",
        "primaryPurpose": "SUPPORTIVE_CARE",
        "maskingInfo": {
          "masking": "TRIPLE",
          "whoMasked": [
            "PARTICIPANT",
            "CARE_PROVIDER",
            "INVESTIGATOR"
          ]
        }
      },
      "enrollmentInfo": {
        "count": 0,
        "type": "ACTUAL"
      }
    },
    "armsInterventionsModule": {
      "armGroups": [
        {
          "label": "bupivacaine S75:R25",
          "type": "EXPERIMENTAL",
          "description": "3 ml for subarachnoid block",
          "interventionNames": [
            "Drug: Bupivacaine"
          ]
        },
        {
          "label": "bupivacaine (S50:R50)",
          "type": "ACTIVE_COMPARATOR",
          "description": "3 ml subarachnoid block",
          "interventionNames": [
            "Drug: Bupivacaine"
          ]
        }
      ],
      "interventions": [
        {
          "type": "DRUG",
          "name": "Bupivacaine",
          "description": "single dose of 15mg by a slow injection rate of 1 ml/s",
          "armGroupLabels": [
            "bupivacaine (S50:R50)",
            "bupivacaine S75:R25"
          ],
          "otherNames": [
            "marcaine"
          ]
        }
      ]
    },
    "outcomesModule": {
      "primaryOutcomes": [
        {
          "measure": "Time of latency for sensory block at T10 dermatome.",
          "description": "Evaluate the sensory block at T10 after the anesthetic injection through sensory stimulation by needle.",
          "timeFrame": "+/- 40 min after injection"
        }
      ],
      "secondaryOutcomes": [
        {
          "measure": "Sensory block duration",
          "description": "Verifying the duration of anesthesia from after puncture till the presence of positive sensitivity by needle stimulation region of the foot.",
          "timeFrame": "+/- 3 hours"
        },
        {
          "measure": "Motor Block Evaluation",
          "description": "Motor block evaluation by Bromage Scale every five minutes after puncture till 20 minutes.",
          "timeFrame": "+/- 30 min"
        },
        {
          "measure": "Maximum cranial dispersion verifying the largest metamer achieved.",
          "description": "Evaluated by needle stimulation every 2 minutes from the removal of post-puncture needle until the maximum extension time.",
          "timeFrame": "+/- 45 min"
        },
        {
          "measure": "Evaluation of the cardiocirculatory and respiratory parameters",
          "description": "Systolic and diastolic blood pressure (SBP and DBP), heart rate (HR), and oxygen saturation (SpO2) are evaluate during the study to measure the safety of cardiocirculatory and respiratory parameters",
          "timeFrame": "+/- 8 hours"
        },
        {
          "measure": "Time of regression of motor block by Bromage Scale",
          "description": "Will be measure the time of recovery of the motor block, the patient have to score note 4 of the Bromage Scale",
          "timeFrame": "+/- 9 - 10 hours"
        },
        {
          "measure": "The residual analgesic effect",
          "description": "Will be evaluated the end of the analgesic effect of the anesthetic solution when the patient asks for pain medication.",
          "timeFrame": "+/- 9-10 hours"
        },
        {
          "measure": "Anesthetic failure",
          "description": "Evaluation of the anesthetic failure (if occur)",
          "timeFrame": "+/- 45 min"
        },
        {
          "measure": "Adverse Events",
          "description": "During the study will be evaluate the presence of adverse event due to the anesthetic.",
          "timeFrame": "+/- 8 - 12 hours"
        }
      ]
    },
    "eligibilityModule": {
      "eligibilityCriteria": "Inclusion Criteria:\n\n* ASA (American Society of Anesthesiologists) I or ASA II\n* Spinal Anaesthesia for lower limb surgery\n* Patient Consent\n\nExclusion Criteria:\n\n* relative or absolute contraindications for spinal anesthesia\n* history of hypersensitivity to the local anesthetics or components\n* opioids for anesthetic adjuvant\n* spinal lesions, peripheral neuropathies or any other neurologic disorders that leads to changes of sensitivity\n* Body mass index = or \\> 35\n* lumbar puncture difficulty\n* ventricular extrasystoles\n* dementia, others loss of cognitive ability\n* difficulty in the spine\n* spinal cord surgery\n* anaphylactic reactions or Stevens-johnson Syndrome\n* polytraumatism\n* alcoholism abuse and use of illicit substance\n* Changes in the blood test\n* Others conditions judged by investigator's opinion",
      "healthyVolunteers": true,
      "sex": "ALL",
      "minimumAge": "18 Years",
      "maximumAge": "80 Years",
      "stdAges": [
        "ADULT",
        "OLDER_ADULT"
      ]
    },
    "contactsLocationsModule": {
      "overallOfficials": [
        {
          "name": "Ligia Mathias, PhD",
          "affiliation": "Irmandade da Santa Casa de Misericórdia de São Paulo",
          "role": "PRINCIPAL_INVESTIGATOR"
        }
      ],
      "locations": [
        {
          "facility": "Hospital Sepaco",
          "city": "São Paulo",
          "state": "São Paulo",
          "country": "Brazil",
          "geoPoint": {
            "lat": -23.5475,
            "lon": -46.63611
          }
        },
        {
          "facility": "Irmandade da Santa Casa de Misericórdia de São Paulo",
          "city": "São Paulo",
          "state": "São Paulo",
          "country": "Brazil",
          "geoPoint": {
            "lat": -23.5475,
            "lon": -46.63611
          }
        }
      ]
    }
  },
  "derivedSection": {
    "miscInfoModule": {
      "versionHolder": "2026-02-18"
    },
    "interventionBrowseModule": {
      "meshes": [
        {
          "id": "D002045",
          "term": "Bupivacaine"
        }
      ],
      "ancestors": [
        {
          "id": "D000813",
          "term": "Anilides"
        },
        {
          "id": "D000577",
          "term": "Amides"
        },
        {
          "id": "D009930",
          "term": "Organic Chemicals"
        },
        {
          "id": "D000814",
          "term": "Aniline Compounds"
        },
        {
          "id": "D000588",
          "term": "Amines"
        }
      ]
    }
  },
  "hasResults": false
}