{
  "protocolSection": {
    "identificationModule": {
      "nctId": "NCT07366723",
      "orgStudyIdInfo": {
        "id": "L2-495"
      },
      "organization": {
        "fullName": "Centro Cardiologico Monzino",
        "class": "OTHER"
      },
      "briefTitle": "The Role of cardIac magNeTic rEsonance in surGical Decision Making in Patients With Severe pRimAry miTral rEgurgitation",
      "officialTitle": "The Role of cardIac magNeTic rEsonance in surGical Decision Making in Patients With Severe pRimAry miTral rEgurgitation (the INTEGRATE Study)",
      "acronym": "INTEGRATE"
    },
    "statusModule": {
      "statusVerifiedDate": "2025-12",
      "overallStatus": "ACTIVE_NOT_RECRUITING",
      "expandedAccessInfo": {
        "hasExpandedAccess": false
      },
      "startDateStruct": {
        "date": "2025-12-01",
        "type": "ACTUAL"
      },
      "primaryCompletionDateStruct": {
        "date": "2029-06-01",
        "type": "ESTIMATED"
      },
      "completionDateStruct": {
        "date": "2029-12-01",
        "type": "ESTIMATED"
      },
      "studyFirstSubmitDate": "2025-12-03",
      "studyFirstSubmitQcDate": "2026-01-16",
      "studyFirstPostDateStruct": {
        "date": "2026-01-26",
        "type": "ACTUAL"
      },
      "lastUpdateSubmitDate": "2026-01-16",
      "lastUpdatePostDateStruct": {
        "date": "2026-01-26",
        "type": "ACTUAL"
      }
    },
    "sponsorCollaboratorsModule": {
      "responsibleParty": {
        "type": "SPONSOR"
      },
      "leadSponsor": {
        "name": "Centro Cardiologico Monzino",
        "class": "OTHER"
      }
    },
    "oversightModule": {
      "oversightHasDmc": false,
      "isFdaRegulatedDrug": false,
      "isFdaRegulatedDevice": false
    },
    "descriptionModule": {
      "briefSummary": "Mitral regurgitation (MR) is the second most frequent valvular heart disease and the second most frequent indication for valve surgery in Europe.\n\nThe management of patients with MV prolapse (MVP) and severe MR is mainly guided by symptoms, left ventricular (LV) dimensions and ejection fraction (EF), pulmonary artery systolic pressure (PASP) and atrial fibrillation (AF) occurrence.\n\nAccording to the ESC/EACTS guidelines, surgical treatment of severe primary MR is indicated (recommendation Class I, Level B) in case of:\n\n* symptomatic patients considered operable by the Heart Team;\n* asymptomatic patients with LV dysfunction, intended as a LVEF ≤ 60% and/or LV end-systolic diameter (LVESD) ≥ 40 mm or LVESD indexed for body mass area (LVESDi) ≥ 20 mm/m2;\n* low-risk asymptomatic patients without LV dysfunction (LVEF \\> 60%, LVESD \\< 40 mm, LVESDi \\< 20 mm/m2) when a durable result is likely, if at least 3 of the following criteria are fulfilled:\n\n  * AF secondary to MR;\n  * PASP value at rest \\> 50 mmHg;\n  * significant left atrium (LA) dilation, intended as LA volume index ≥ 60 mL/m2 or diameter ≥ 55 mm\n  * concomitant secondary tricuspid regurgitation ≥ moderate.\n\nSurgery should be considered (recommendation Class IIa, Level B) in asymptomatic patients with preserved LV function (LVEF \\> 60%, LVESD \\< 40 mm, LVESDi \\< 20 mm/m2), when one of the following findings is present1:\n\n* AF secondary to MR;\n* PASP value at rest \\> 50 mmHg;\n* LA volume index ≥ 60 mL/m2 or diameter ≥ 55 mm, provided surgical risk is low, surgery is performed in a Heart Valve Center and a durable MV repair is likely.\n\nPreliminary data suggest that in patients with MVP, especially with Barlow's disease phenotype, left-sided chambers' enlargement and functional impairment may be disproportionate related to MR grade. Indeed, patients with BD and ≤ mild-to-moderate MR show larger LA and LV dimensions as compared to controls matched for age, gender and cardiovascular risk factors. These findings challenge the assumption that LA and LV remodeling is a direct effect of volume overload, with possible implications regarding the indication for MV intervention.\n\nOn the other hand, low mortality and good durability of valve repair has led some experienced centers to perform also early surgery, namely in any asymptomatic patient with severe MR, normal LV size and function, regular sinus rhythm, normal PASP and normal LA size, as long as surgical risk is very low and likelihood of successful valve repair is high. However, some studies have demonstrated that asymptomatic patients with severe degenerative MR can be safely followed up in experienced hands and remain free of indications for surgery for extensive periods of time. A watchful waiting strategy resulted in timely referral to surgery, excellent long-term survival, and good surgical outcomes, though requiring careful and active surveillance. Several authors agree that prospective randomized trials comparing active surveillance and early elective surgery are needed. There are also data suggesting that MR quantification by CMR has better discriminative power in identifying asymptomatic patients with degenerative MR and adverse outcomes as compared to the echocardiographic-derived integrative approach. Further prospective studies are necessary to validate these preliminary findings.",
      "detailedDescription": "The present study is a multicenter, prospective, interventional, open randomized controlled trial. Patients will be screened for study eligibility by the clinical research staff of each investigational site. Patients meeting all inclusion criteria will be asked to sign an informed consent document prior to any trial-specific examinations and/or procedures, provided they do not have any of the exclusion criteria. After signing the informed consent, a structured interview will be performed and a clinical history obtained, assessing the presence of common cardiac risk factors, symptoms, and drug therapy (with a specific focus on anti-remodeling drugs, such as angiotensin-converting enzyme inhibitors/angiotensin II receptor blockers and mineralocorticoid receptor blockers). A Quality of Life (QoL) questionnaire will be administered13. Physical examination, rest ECG, CMR and a cardiopulmonary exercise test (CPET) will be also performed.\n\nSubjects will be assigned a subject number upon enrolment. Afterwards, they will be randomized in a 1:1 ratio to a CMR-based strategy (unblinded CMR) or usual care1 (blinded CMR).\n\nA randomization list will be generated using SAS statistical software (version 9.4, SAS Institute, Cary, NC, USA) and will be created by the Biostatistics Unit of Centro Cardiologico Monzino IRCCS, without direct contact with trial participants or involvement in the assessment of study eligibility.\n\nAfter randomization, patients will be classified as follows (Figure 1 and 2):\n\n* group A: patients with severe MR, as assessed by TTE, with less than severe MR documented by CMR, undergoing clinical follow-up;\n* group B: patients with severe MR, as quantified by both TTE and CMR, undergoing surgery;\n* group C: patients with severe MR, as assessed by TTE, undergoing surgery as per clinical practice.\n\nAfter patients of group B and C have undergone surgery, baseline CMR of Group C will be unblinded. Then, patients of group C will be furtherly divided into two subgroups: those having less than severe MR as assessed by CMR (subgroup C1) and those having severe MR (subgroup C2).\n\nAt 1-year and 2-year follow-up after enrolment (group A) and after surgery (groups B and C), all patients will undergo a complete evaluation including a clinical interview and physical examination, administration of QoL questionnaires, performance of TTE, CMR and CPET."
    },
    "conditionsModule": {
      "conditions": [
        "Mitral Valve Prolapse",
        "Mitral Regurgitation"
      ]
    },
    "designModule": {
      "studyType": "INTERVENTIONAL",
      "phases": [
        "NA"
      ],
      "designInfo": {
        "allocation": "RANDOMIZED",
        "interventionModel": "PARALLEL",
        "interventionModelDescription": "Patients will be randomized in a 1:1 ratio to a CMR-based strategy (unblinded CMR) or usual care (blinded CMR). A randomization list will be generated using SAS statistical software and will be created by the Biostatistics Unit of Centro Cardiologico Monzino IRCCS, without direct contact with trial participants or involvement in the assessment of study eligibility.\n\nAfter randomization, patients will be classified as follows:\n\n* group A: patients with severe MR, as assessed by TTE, with less than severe MR documented by CMR, undergoing clinical follow-up;\n* group B: patients with severe MR, as quantified by both TTE and CMR, undergoing surgery;\n* group C: patients with severe MR, as assessed by TTE, undergoing surgery as per clinical practice.\n\nAfter surgery, baseline CMR of Group C will be unblinded. Then, patients of group C will be furtherly divided into two subgroups: those having less than severe MR as assessed by CMR (subgroup C1) and those with severe MR (subgroup C2).",
        "primaryPurpose": "OTHER",
        "maskingInfo": {
          "masking": "SINGLE",
          "whoMasked": [
            "PARTICIPANT"
          ]
        }
      },
      "enrollmentInfo": {
        "count": 260,
        "type": "ACTUAL"
      }
    },
    "armsInterventionsModule": {
      "armGroups": [
        {
          "label": "Blinded CMR - Group C1",
          "type": "ACTIVE_COMPARATOR",
          "description": "Patients undergoing sugery based on TTE, showing less than severe MR by CMR",
          "interventionNames": [
            "Procedure: mitral valve surgery"
          ]
        },
        {
          "label": "Unblinded CMR - Group A",
          "type": "OTHER",
          "description": "Patients with severe MR, as assessed by TTE, with less than severe MR documented by CMR (Group A), undergo clinical follow-up.",
          "interventionNames": [
            "Other: Clinical Follow up"
          ]
        },
        {
          "label": "Unblinded CMR - Group B",
          "type": "ACTIVE_COMPARATOR",
          "description": "Patients with severe MR, as quantified by both TTE and CMR, undergo surgery.",
          "interventionNames": [
            "Procedure: mitral valve surgery"
          ]
        },
        {
          "label": "Blinded CMR - Group C2",
          "type": "ACTIVE_COMPARATOR",
          "description": "Patients undergoing surgery based on TTE, showing severe MR by CMR",
          "interventionNames": [
            "Procedure: mitral valve surgery"
          ]
        }
      ],
      "interventions": [
        {
          "type": "PROCEDURE",
          "name": "mitral valve surgery",
          "description": "mitral valve repair or replacement",
          "armGroupLabels": [
            "Blinded CMR - Group C1",
            "Blinded CMR - Group C2",
            "Unblinded CMR - Group B"
          ]
        },
        {
          "type": "OTHER",
          "name": "Clinical Follow up",
          "description": "Patients undergo clinical active surveillance.",
          "armGroupLabels": [
            "Unblinded CMR - Group A"
          ]
        }
      ]
    },
    "outcomesModule": {
      "primaryOutcomes": [
        {
          "measure": "Proportion of adverse and reverse LV remodeling",
          "description": "The primary efficacy aim is to demonstrate that in patients managed based on CMR results (\"unblinded CMR\") the proportion of inappropriate clinical decisions is lower as compared to the proportion of inappropriate clinical decisions in patients managed on the basis of TTE results (\"blinded CMR\").\n\nIn group A:\n\n* clinical decision will be considered appropriate in case reverse LV remodeling, or no LV remodeling is observed by CMR at 2-year follow-up\n* clinical decision will be considered inappropriate in case adverse LV remodeling by CMR occurs at 2-year follow-up.\n\nIn groups B and C:\n\n* clinical decision will be considered appropriate in case reverse LV remodeling by CMR occurs at 2-year follow-up\n* clinical decision will be considered inappropriate in case adverse LV remodeling, or no LV remodeling is observed by CMR at 2-year follow-up.\n\nOperational definitions:\n\nAdverse LV remodeling=increase in LV EDV \\>/= 10% vs baseline. Reverse LV remodeling=reduction in LV EDV \\>/= 30% vs. baseline.",
          "timeFrame": "up to 24 months"
        }
      ],
      "secondaryOutcomes": [
        {
          "measure": "Rate of composite clinical endpoints",
          "description": "To demonstrate that freedom from a composite of\n\n* hospitalization for heart failure\n* Class I indications for surgery\n* atrial fibrillation documentation\n* PASP \\> 50 mmHg at TTE in the \"unblinded CMR\" groups is non inferior to freedom from the same events observed in the \"blinded CMR\" groups at 2-year follow-up, by more than a clinically relevant margin (at most 3%).\n\nHeart failure hospitalization is defined as an event meeting the following criteria:\n\n* subject has clinical signs and/or symptoms of heart failure, requires hospitalization in the hospital for at least 24h, and requires intravenous or invasive treatment for heart failure;\n* subject arrives in the emergency department with clinical presentation meeting the criteria of heart failure but dies in the emergency department before hospital admission.",
          "timeFrame": "up to 24 months"
        },
        {
          "measure": "rate of mortality",
          "description": "To demonstrate that freedom from cardiovascular death at 2-year follow-up in Groups A+B is non inferior to freedom from the same event in Groups C1+C2.\n\nOperational definitions: cardiovascular death at 2-year follow-up is intended as any one of the following: any death due to cardiac cause (e.g. myocardial infarction, worsening heart failure); unwitnessed death and death of unknown cause; death caused by non-coronary vascular conditions such as cerebrovascular disease, pulmonary embolism, ruptured aortic aneurysm, or other vascular disease.",
          "timeFrame": "up to 24 months"
        },
        {
          "measure": "Measure of exercise capacity",
          "description": "To demonstrate that exercise capacity at 2-year follow-up, as assessed by CPET parameters (peak VO2), is non inferior in the \"unblinded CMR\" groups as compared to \"blinded CMR\" groups.",
          "timeFrame": "up to 24 moths"
        },
        {
          "measure": "SF-36 Health Survey questionnaire",
          "description": "To demonstrate that quality of life at 2-year follow-up, as assessed by the SF-36 Health Survey questionnaire, (from 0 to 100 which is best condition ) is non inferior in the \"unblinded CMR\" groups as compared to \"blinded CMR\" groups.",
          "timeFrame": "up to 24 months"
        }
      ]
    },
    "eligibilityModule": {
      "eligibilityCriteria": "Inclusion Criteria:\n\n* age ≥ 18 years;\n* patients agree to all provisions of the protocol;\n* patient can give informed consent;\n* TTE diagnosis of MVP (defined as a systolic displacement of one or both mitral leaflets ≥ 2 mm above the plane of the MV annulus in long-axis views), and chronic severe MR;\n* no symptoms;\n* LVEF \\> 60%, LVESD \\< 40 mm and LVESDi \\< 20 mm/m2;\n* sinus rhythm;\n* PASP value at rest \\< 50 mmHg;\n* LA volume index ≥ 60 mL/m2 or diameter ≥ 55 mm or normal LA size if likelihood of a successful and durable repair without residual MR is \\>95% and expected mortality rate is \\<1%\n* ongoing adequate treatment per applicable standards;\n* patient referred for isolated MV repair or replacement;\n* willingness to undergo TTE, CMR and CPET at different timepoints\n\nExclusion Criteria:\n\n* inability to provide informed consent;\n* pregnancy or planned pregnancy within next 2 years;\n* poor TTE image quality;\n* usual contraindications to CMR and/or to gadolinium administration;\n* inability to sustain a breath hold;\n* known intracardiac shunts;\n* coexistence of other cardiomyopathies or other \\> mild valve diseases;\n* untreated clinically significant coronary artery disease requiring revascularization;\n* planned concomitant cardiac surgical procedures (e.g. other valve procedures, or coronary artery bypass);\n* need for an emergent/urgent surgery for any reason or any planned cardiac surgery within the next months;\n* hemodynamic instability requiring inotropic support or mechanical heart assistance;\n* sustained cardiac arrhythmias;\n* active endocarditis;\n* like expectancy \\< 12 months due to non-cardiac conditions.",
      "healthyVolunteers": false,
      "sex": "ALL",
      "minimumAge": "18 Years",
      "stdAges": [
        "ADULT",
        "OLDER_ADULT"
      ]
    },
    "contactsLocationsModule": {
      "overallOfficials": [
        {
          "name": "Gianluca Pontone, MD",
          "affiliation": "Centro Cardiologico Monzino, IRCCS Milan 20131",
          "role": "PRINCIPAL_INVESTIGATOR"
        }
      ],
      "locations": [
        {
          "facility": "Centro Cardiologico Monzino, IRCCS",
          "city": "Milan",
          "state": "MI",
          "zip": "20131",
          "country": "Italy",
          "geoPoint": {
            "lat": 45.46427,
            "lon": 9.18951
          }
        }
      ]
    }
  },
  "derivedSection": {
    "miscInfoModule": {
      "versionHolder": "2026-02-18"
    },
    "conditionBrowseModule": {
      "meshes": [
        {
          "id": "D008945",
          "term": "Mitral Valve Prolapse"
        },
        {
          "id": "D008944",
          "term": "Mitral Valve Insufficiency"
        }
      ],
      "ancestors": [
        {
          "id": "D016127",
          "term": "Heart Valve Prolapse"
        },
        {
          "id": "D006349",
          "term": "Heart Valve Diseases"
        },
        {
          "id": "D006331",
          "term": "Heart Diseases"
        },
        {
          "id": "D002318",
          "term": "Cardiovascular Diseases"
        }
      ]
    }
  },
  "hasResults": false
}